include/__about__.py
include/__init__.py
include/inhibit.py
include/base/__init__.py
include/base/import_hook.py
include/encoded/__init__.py
include/encoded/import_hook.py
include/files/__init__.py
include/files/import_hook.py
include/mount/__init__.py
include-0.2.2.dist-info/DESCRIPTION.rst
include-0.2.2.dist-info/METADATA
include-0.2.2.dist-info/RECORD
include-0.2.2.dist-info/WHEEL
include-0.2.2.dist-info/metadata.json
include-0.2.2.dist-info/top_level.txt
test_include/__init__.py
test_include/functionality.py
