Metadata-Version: 1.1
Name: include
Version: 0.2.2
Summary: Dynamic import from files and other sources
Home-page: https://github.com/maxfischer2781/include
Author: Max Fischer
Author-email: maxfischer2781@gmail.com
License: MIT
Keywords: import include eval exec pickle multiprocess
Platform: UNKNOWN
Classifier: Development Status :: 4 - Beta
Classifier: Intended Audience :: Developers
Classifier: Intended Audience :: System Administrators
Classifier: Topic :: System :: Monitoring
Classifier: Programming Language :: Python :: 2
Classifier: Programming Language :: Python :: 2.6
Classifier: Programming Language :: Python :: 2.7
Classifier: Programming Language :: Python :: 3
Classifier: Programming Language :: Python :: 3.3
Classifier: Programming Language :: Python :: 3.4
Classifier: Programming Language :: Python :: 3.5
Classifier: Programming Language :: Python :: 3.6
